ffmpeg_downloader/__init__.py
ffmpeg_downloader/__main__.py
ffmpeg_downloader/_backend.py
ffmpeg_downloader/_config.py
ffmpeg_downloader/_download_helper.py
ffmpeg_downloader/_linux.py
ffmpeg_downloader/_macos.py
ffmpeg_downloader/_path.py
ffmpeg_downloader/_progress.py
ffmpeg_downloader/_win32.py
ffmpeg_downloader/ffdl.py
ffmpeg_downloader/qt/__init__.py
ffmpeg_downloader/qt/__main__.py
ffmpeg_downloader/qt/qt_compat.py
ffmpeg_downloader/qt/wizard.py
ffmpeg_downloader-0.4.1.dist-info/licenses/LICENSE
ffmpeg_downloader-0.4.1.dist-info/METADATA
ffmpeg_downloader-0.4.1.dist-info/WHEEL
ffmpeg_downloader-0.4.1.dist-info/entry_points.txt
ffmpeg_downloader-0.4.1.dist-info/top_level.txt
ffmpeg_downloader-0.4.1.dist-info/RECORD
