Metadata-Version: 2.4
Name: ffmpeg_downloader
Version: 0.4.1
Summary: FFmpeg Release Build Downloader
License: GPL-2.0 License
Project-URL: Repository, https://github.com/python-ffmpegio/python-ffmpeg-downloader
Project-URL: Issues, https://github.com/python-ffmpegio/python-ffmpegio-downloader/issues
Project-URL: Pull_Requests, https://github.com/python-ffmpegio/python-ffmpegio-downloader/pulls
Keywords: multimedia,ffmpeg,ffprobe,download
Classifier: Development Status :: 4 - Beta
Classifier: License :: OSI Approved :: GNU General Public License v2 (GPLv2)
Classifier: Topic :: Multimedia :: Sound/Audio
Classifier: Topic :: Multimedia :: Sound/Audio :: Capture/Recording
Classifier: Topic :: Multimedia :: Sound/Audio :: Conversion
Classifier: Topic :: Multimedia :: Video
Classifier: Topic :: Multimedia :: Video :: Capture
Classifier: Topic :: Multimedia :: Video :: Conversion
Classifier: Programming Language :: Python :: 3.8
Classifier: Programming Language :: Python :: 3.9
Classifier: Programming Language :: Python :: 3.10
Classifier: Programming Language :: Python :: 3.11
Classifier: Programming Language :: Python :: 3.12
Requires-Python: >=3.7
License-File: LICENSE
Requires-Dist: requests
Requires-Dist: tqdm>=4.40.0
Requires-Dist: platformdirs
Requires-Dist: packaging
Dynamic: license-file
